README.md
mobile_block.py
setup.py
mobile_block.egg-info/PKG-INFO
mobile_block.egg-info/SOURCES.txt
mobile_block.egg-info/dependency_links.txt
mobile_block.egg-info/requires.txt
mobile_block.egg-info/top_level.txt