Metadata-Version: 1.0
Name: mobile-block
Version: 0.0.4
Summary: MobileNet-style blocks for PyTorch
Home-page: https://github.com/SF-Zhou/mobile-block
Author: SF-Zhou
Author-email: sfzhou.scut@gmail.com
License: UNKNOWN
Keywords: MobileNet Block PyTorch
Platform: UNKNOWN
